dify_plugin/__init__.py
dify_plugin/cli.py
dify_plugin/commands/__init__.py
dify_plugin/commands/generate_docs.py
dify_plugin/config/__init__.py
dify_plugin/config/config.py
dify_plugin/config/integration_config.py
dify_plugin/config/logger_format.py
dify_plugin/core/__init__.py
dify_plugin/core/documentation/__init__.py
dify_plugin/core/documentation/generator.py
dify_plugin/core/documentation/schema_doc.py
dify_plugin/core/entities/__init__.py
dify_plugin/core/entities/invocation.py
dify_plugin/core/entities/message.py
dify_plugin/core/entities/plugin/__init__.py
dify_plugin/core/entities/plugin/io.py
dify_plugin/core/entities/plugin/parameter_type.py
dify_plugin/core/entities/plugin/request.py
dify_plugin/core/entities/plugin/setup.py
dify_plugin/core/plugin_executor.py
dify_plugin/core/plugin_registration.py
dify_plugin/core/runtime.py
dify_plugin/core/server/__base/__init__.py
dify_plugin/core/server/__base/filter_reader.py
dify_plugin/core/server/__base/request_reader.py
dify_plugin/core/server/__base/response_writer.py
dify_plugin/core/server/__base/writer_entities.py
dify_plugin/core/server/__init__.py
dify_plugin/core/server/io_server.py
dify_plugin/core/server/router.py
dify_plugin/core/server/serverless/__init__.py
dify_plugin/core/server/serverless/request_reader.py
dify_plugin/core/server/serverless/response_writer.py
dify_plugin/core/server/stdio/__init__.py
dify_plugin/core/server/stdio/request_reader.py
dify_plugin/core/server/stdio/response_writer.py
dify_plugin/core/server/tcp/__init__.py
dify_plugin/core/server/tcp/request_reader.py
dify_plugin/core/utils/__init__.py
dify_plugin/core/utils/class_loader.py
dify_plugin/core/utils/http_parser.py
dify_plugin/core/utils/position_helper.py
dify_plugin/core/utils/yaml_loader.py
dify_plugin/entities/__init__.py
dify_plugin/entities/agent.py
dify_plugin/entities/datasource.py
dify_plugin/entities/datasource_manifest.py
dify_plugin/entities/endpoint.py
dify_plugin/entities/invoke_message.py
yxc_dify_plugin-0.5.0.dist-info/METADATA
yxc_dify_plugin-0.5.0.dist-info/WHEEL
yxc_dify_plugin-0.5.0.dist-info/entry_points.txt
yxc_dify_plugin-0.5.0.dist-info/licenses/LICENSE
yxc_dify_plugin-0.5.0.dist-info/RECORD
